lhsmdu/__init__.py
lhsmdu-1.1.dist-info/LICENSE
lhsmdu-1.1.dist-info/METADATA
lhsmdu-1.1.dist-info/WHEEL
lhsmdu-1.1.dist-info/top_level.txt
lhsmdu-1.1.dist-info/RECORD
