Metadata-Version: 2.1
Name: lhsmdu
Version: 1.1
Summary: This is an implementation of Latin Hypercube Sampling with Multi-Dimensional Uniformity (LHS-MDU) from Deutsch and Deutsch, "Latin hypercube sampling with multidimensional uniformity.
Home-page: http://github.com/sahilm89/lhsmdu
Author: Sahil Moza
Author-email: sahil.moza@gmail.com
License: MIT
Platform: UNKNOWN
Requires-Dist: numpy
Requires-Dist: scipy
